qdrant_odm/__init__.py
qdrant_odm/crud.py
qdrant_odm/dataclass.py
qdrant_odm/model.py
qdrant_odm/index/__init__.py
qdrant_odm/index/payload.py
qdrant_odm/index/vectors.py
qdrant_odm-0.0.4.dist-info/METADATA
qdrant_odm-0.0.4.dist-info/WHEEL
qdrant_odm-0.0.4.dist-info/top_level.txt
qdrant_odm-0.0.4.dist-info/RECORD
