Metadata-Version: 2.2
Name: qdrant-odm
Version: 0.0.4
Summary: Object-Document Mapping Library for Qdrant
Requires-Python: >=3.11
Requires-Dist: loguru>=0.7.2
Requires-Dist: qdrant-client>=1.12.1
